htagui/__init__.py
htagui/all.py
htagui/basics/__init__.py
htagui/basics/bases.py
htagui/bulma/__init__.py
htagui/bulma/bases.py
htagui/common.py
htagui/containers.py
htagui/dialog.py
htagui/fileupload.py
htagui/flex.py
htagui/fluent/__init__.py
htagui/fluent/bases.py
htagui/form.py
htagui/ifields.py
htagui/javascripts.py
htagui/md/__init__.py
htagui/md/bases.py
htagui/shoelace/__init__.py
htagui/shoelace/bases.py
htagui/sortables.py
htagui/splitters.py
htagui/tabs.py
htagui-0.6.6.dist-info/LICENSE
htagui-0.6.6.dist-info/METADATA
htagui-0.6.6.dist-info/WHEEL
htagui-0.6.6.dist-info/RECORD
