Metadata-Version: 2.3
Name: htagui
Version: 0.6.6
Summary: GUI toolkit for creating beautiful applications for mobile, web, and desktop from a single python3 codebase
License: MIT
Keywords: htag,gui,electron,cef,asyncio,guy,desktop,web,mobile,http,websocket,html,pyscript
Author: manatlan
Author-email: manatlan@gmail.com
Requires-Python: >=3.7,<4.0
Classifier: License :: OSI Approved :: Apache Software License
Classifier: License :: OSI Approved :: MIT License
Classifier: Operating System :: OS Independent
Classifier: Programming Language :: Python :: 3
Classifier: Programming Language :: Python :: 3.7
Classifier: Programming Language :: Python :: 3.8
Classifier: Programming Language :: Python :: 3.9
Classifier: Programming Language :: Python :: 3.10
Classifier: Programming Language :: Python :: 3.11
Classifier: Programming Language :: Python :: 3.12
Classifier: Programming Language :: Python :: 3.13
Classifier: Topic :: Software Development :: Build Tools
Classifier: Topic :: Software Development :: Libraries :: Python Modules
Requires-Dist: htag (>=0.103)
Project-URL: Documentation, https://github.com/manatlan/htagui
Project-URL: Homepage, https://github.com/manatlan/htagui
Project-URL: Repository, https://github.com/manatlan/htagui
